prices/__init__.py
prices/discount.py
prices/money.py
prices/money_range.py
prices/tax.py
prices/taxed_money.py
prices/taxed_money_range.py
prices/utils.py
prices-1.1.0.dist-info/LICENSE
prices-1.1.0.dist-info/METADATA
prices-1.1.0.dist-info/WHEEL
prices-1.1.0.dist-info/top_level.txt
prices-1.1.0.dist-info/RECORD
