Metadata-Version: 1.1
Name: prices
Version: 1.1.0
Summary: Python price handling for humans
Home-page: https://github.com/mirumee/prices
Author: Mirumee Software
Author-email: hello@mirumee.com
License: BSD
Platform: any
Classifier: Intended Audience :: Developers
Classifier: License :: OSI Approved :: BSD License
Classifier: Operating System :: OS Independent
Classifier: Programming Language :: Python
Classifier: Programming Language :: Python :: 3.5
Classifier: Programming Language :: Python :: 3.6
Classifier: Programming Language :: Python :: 3.7
Classifier: Programming Language :: Python :: 3.8
Classifier: Topic :: Software Development :: Libraries :: Python Modules
